ocflib/__init__.py
ocflib/account/__init__.py
ocflib/account/creation.py
ocflib/account/mail_templates/account-created.jinja
ocflib/account/mail_templates/account-rejected.jinja
ocflib/account/manage.py
ocflib/account/search.py
ocflib/account/submission.py
ocflib/account/utils.py
ocflib/account/validators.py
ocflib/infra/__init__.py
ocflib/infra/discourse.py
ocflib/infra/github.py
ocflib/infra/hosts.py
ocflib/infra/kanboard.py
ocflib/infra/kerberos.py
ocflib/infra/ldap.py
ocflib/infra/mysql.py
ocflib/infra/net.py
ocflib/infra/rt.py
ocflib/lab/__init__.py
ocflib/lab/hours.py
ocflib/lab/ocfstats.sql
ocflib/lab/staff_hours.py
ocflib/lab/stats.py
ocflib/misc/__init__.py
ocflib/misc/mail.py
ocflib/misc/ocfshorturls.sql
ocflib/misc/shell.py
ocflib/misc/shorturls.py
ocflib/misc/validators.py
ocflib/misc/whoami.py
ocflib/org/__init__.py
ocflib/org/meeting_hours.py
ocflib/printing/__init__.py
ocflib/printing/ocfprinting.sql
ocflib/printing/printers.py
ocflib/printing/quota.py
ocflib/ucb/__init__.py
ocflib/ucb/cas.py
ocflib/ucb/directory.py
ocflib/ucb/groups.py
ocflib/vhost/__init__.py
ocflib/vhost/application.py
ocflib/vhost/mail.py
ocflib/vhost/ocfmail.sql
ocflib/vhost/web.py
ocflib-2025.10.16.dist-info/METADATA
ocflib-2025.10.16.dist-info/WHEEL
ocflib-2025.10.16.dist-info/licenses/LICENSE
ocflib-2025.10.16.dist-info/RECORD
