Metadata-Version: 2.4
Name: ocflib
Version: 2025.10.16
Summary: libraries for account and server management
License-File: LICENSE
Author: Open Computing Facility
Author-email: help@ocf.berkeley.edu
Requires-Python: >=3.7,<3.12
Classifier: Programming Language :: Python :: 3
Classifier: Programming Language :: Python :: 3.7
Classifier: Programming Language :: Python :: 3.8
Classifier: Programming Language :: Python :: 3.9
Classifier: Programming Language :: Python :: 3.10
Classifier: Programming Language :: Python :: 3.11
Requires-Dist: attrs (>=22.2.0)
Requires-Dist: cached-property (>=1.5.2,<2.0.0)
Requires-Dist: dnspython (>=2.1.0,<3.0.0)
Requires-Dist: jinja2 (>=3.0.3,<4.0.0)
Requires-Dist: ldap3 (>=2.9.1,<3.0.0)
Requires-Dist: pexpect (>=4.9.0,<5.0.0)
Requires-Dist: pycryptodome (>=3.19.0,<4.0.0)
Requires-Dist: pygithub (>=1.56)
Requires-Dist: pymysql (>=1.0.2,<2.0.0)
Requires-Dist: pysnmp (>=4.4.12,<5.0.0)
Requires-Dist: pyyaml (>=6.0.1,<7.0.0)
Requires-Dist: redis (>=4.3.6)
Requires-Dist: requests (>=2.26.1,<3.0.0)
Requires-Dist: sqlalchemy (>=1.4.52,<2.0.0)
Requires-Dist: zxcvbn (>=4.5.0,<5.0.0)
